data_ram.sv
module data_ram #(
    parameter WIDTH = 32
)(
    input logic                clk,
    input logic                Data_WE,
    input logic  [WIDTH -1:0]  Data_addr,
    input logic [WIDTH -1:0]   Data_WD,
    output logic  [WIDTH -1:0] Data_RD
);


logic [7:0] data_mem [32'h00001FFF:32'h00001000];

initial begin
        $display("Loading Data_mem.");
        $readmemh("data.mem", data_mem);
end;

always_comb begin
    Data_RD = {data_mem[Data_addr+3], data_mem[Data_addr+2], data_mem[Data_addr+1], data_mem[Data_addr]};
end

always_ff @(posedge clk)
    if (Data_WE) begin
    data_mem[Data_addr+3] = Data_WD[31:24];
    data_mem[Data_addr+2] = Data_WD[23:16];
    data_mem[Data_addr+1] = Data_WD[15:8];
    data_mem[Data_addr] = Data_WD[7:0];
    end

endmodule

ALU_unit.sv
module ALU_unit #(
    parameter WIDTH = 32
)(
    input   logic [WIDTH-1:0] ALUop1,
    input   logic [WIDTH-1:0] RegOp2,
    input   logic [WIDTH-1:0] ImmOp,
    output  logic [WIDTH-1:0] ALUout,
    input   logic [3:0]       ALUctrl,
    input   logic             ALUsrc,
    output  logic             EQ
);

logic [WIDTH-1:0] ALUop2;

always_comb begin
    ALUop2 = ALUsrc ? ImmOp : RegOp2; 
    case (ALUctrl)
        4'b0000: ALUout = ALUop1 + ALUop2;
        4'b0001: ALUout = ALUop1 - ALUop2;
        4'b0010: ALUout = ALUop1 << ALUop2[4:0];
        4'b0011: 
            if ( ~ALUop1[31] & ~ ALUop2[31])
                ALUout <= (ALUop1[30:0] < ALUop2[30:0]);
            else if (ALUop1[31] & ~ ALUop2[31])
                ALUout <= 32'b1;
            else if (~ALUop1[31] & ALUop2[31])
                ALUout <= 32'b0;
            else
                ALUout <= (ALUop1[30:0] > ALUop2[30:0]);
        4'b0100: ALUout = (ALUop1 < ALUop2);
        4'b0101: ALUout = ALUop1 | ALUop2;
        4'b0110: ALUout = ALUop1 >> ALUop2[4:0];
        4'b0111: ALUout = ALUop1 >>> ALUop2[4:0];
        4'b1000: ALUout = ALUop1 | ALUop2;
        4'b1001: ALUout = ALUop1 & ALUop2;
    endcase
    EQ = (ALUop1 == ALUop2);
end
endmodule

signextend.sv
module signextend #(
    parameter Width = 32
)(
    input  logic [Width-1:0] instr,
    input  logic [2:0]       ImmSrc,
    output logic [Width-1:0] ImmOp
);


// assign ImmOp = ImmSrc ? { {20{instr[31]}}, instr[31:20] } : { {20{instr[31]}}, instr[31], instr[7], instr[30:25], instr[11:8], 1'b0 };  

always_comb

    case(ImmSrc)

    3'b00:     ImmOp = { {20{instr[31]}}, instr[31:20] }; //I-type
    3'b01:     ImmOp = { {20{instr[31]}}, instr[31:25], instr[11:7] }; //S-type
    3'b10:     ImmOp = { {19{instr[31]}}, instr[31], instr[7], instr[30:25], instr[11:8], 1'b0 }; //B-type
    3'b11:     ImmOp = {32'b0}; //R-Type (has no immediate)
    3'b100:    ImmOp = { {12{instr[31]}}, instr[31:12] }; // U-Type
    3'b101:    ImmOp = { {11{instr[31]}}, instr[31], instr[19:12], instr[20], instr[30:21], 1'b0 };  // J-type     
    default:   ImmOp = { {20{instr[31]}}, instr[31:20] }; //default I type
    
    endcase



endmodule

RegFile.sv
module RegFile #(
    parameter D_WIDTH = 32,
              A_WIDTH = 5
)(
    input  logic                clk,
    input  logic                WE3,
    input  logic                ResultSrc,
    input  logic                PCJump,
    input  logic                trigger,
    input  logic [D_WIDTH-1:0]  PC,
    input  logic [A_WIDTH-1:0]  AD1,
    input  logic [A_WIDTH-1:0]  AD2,
    input  logic [A_WIDTH-1:0]  AD3,
    input  logic [D_WIDTH-1:0]  ALUout,
    input  logic [D_WIDTH-1:0]  Data_RD,
    output logic [D_WIDTH-1:0]  RD1,
    output logic [D_WIDTH-1:0]  RD2,
    output logic [D_WIDTH-1:0]  a0
);

reg [D_WIDTH-1:0] reg_file [31:0];

logic [D_WIDTH-1:0] WD3;
logic [D_WIDTH-1:0] result;

assign WD3 = PCJump ? PC + 4 : result;
assign result = ResultSrc ? Data_RD : ALUout;

// initial begin
//     // for (i = 0; i < 2**A_WIDTH -1; i++){
//     //     reg_file[i] <= 32'b0
//     // }
//     $display("Loading RegFile.");
//     $readmemh("RegFile.mem", reg_file);
// end;
assign reg_file[0] = 32'b0;

always_ff @( posedge clk ) begin 

    if (WE3) reg_file[AD3] = WD3;
    
end

always_comb begin
    RD1 = reg_file[AD1];
    RD2 = reg_file[AD2];
    a0 <= reg_file[10];
    reg_file[5] <= trigger;
end

endmodule

control_unit.sv
module control_unit #(
    parameter Width = 32
)(
    input  logic           EQ,
    input  logic [Width-1:0] instr,
    output logic           RegWrite,
    output logic           ResultSrc,
    output logic           ALUsrc,
    output logic [1:0]     PCsrc,
    output logic [2:0]     ALUctrl,
    output logic [2:0]     ImmSrc,
    output logic           Data_WE,
    output logic           PCJump

);

logic [2:0] funct3;
logic [6:0] funct7;
logic [6:0] opcode;

assign funct3 = instr[14:12];
assign funct7 = instr[31:25];
assign opcode = instr[6:0];


always_comb


case(opcode)

//R-type instructions
     7'b0110011: 

                case(funct3)
            
                3'b000: 
                    if (funct7 == 7'b0) //add 
                        begin
                            ALUctrl = 4'b0000;
                            RegWrite = 1;
                            ImmSrc = 3'b011;
                            ALUsrc = 0;
                            PCsrc = 2'b0;
                            ResultSrc = 0;
                            Data_WE = 0;
                            PCJump = 0;
                        end
                    else //sub
                        begin
                            ALUctrl = 4'b0001;
                            RegWrite = 1;
                            ImmSrc = 3'b011;
                            ALUsrc = 0;
                            PCsrc = 2'b0;
                            ResultSrc = 0;
                            Data_WE = 0;
                            PCJump = 0;
                        end                     
                            

                3'b001: //shift left logical (sll)
                    begin
                        ALUctrl = 4'b0010;
                        RegWrite = 1;
                        ImmSrc = 3'b011;
                        ALUsrc = 0;
                        PCsrc = 2'b0;
                        ResultSrc = 0;
                        Data_WE = 0;
                        PCJump = 0;
                    end

                3'b010: //set less than
                        begin
                            ALUctrl = 4'b0011;
                            RegWrite = 1;
                            ImmSrc = 3'b011;
                            ALUsrc = 0;
                            PCsrc = 2'b0;
                            ResultSrc = 0;
                            Data_WE = 0;
                            PCJump = 0;
                        end 
                
                3'b011: //set less than unsigned
                
                        begin
                            ALUctrl = 4'b0100;
                            RegWrite = 1;
                            ImmSrc = 3'b011;
                            ALUsrc = 0;
                            PCsrc = 2'b0;
                            ResultSrc = 0;
                            Data_WE = 0;
                            PCJump = 0;
                        end
                
                3'b100: //xor
                        begin
                            ALUctrl = 4'b0101;
                            RegWrite = 1;
                            ImmSrc = 3'b011;
                            ALUsrc = 0;
                            PCsrc = 2'b0;
                            ResultSrc = 0;
                            Data_WE = 0;
                            PCJump = 0;
                        end
                
                3'b101: 

                    if (funct7 == 7'b0) //shift right logical
                        begin
                            ALUctrl = 4'b0110;
                            RegWrite = 1;
                            ImmSrc = 3'b011;
                            ALUsrc = 0;
                            PCsrc = 2'b0;
                            ResultSrc = 0;
                            Data_WE = 0;
                            PCJump = 0;
                        end

                    else //shift right arithmetic
                        begin
                            ALUctrl = 4'b0111;
                            RegWrite = 1;
                            ImmSrc = 3'b011;
                            ALUsrc = 0;
                            PCsrc = 2'b0;
                            ResultSrc = 0;
                            Data_WE = 0;
                            PCJump = 0;
                        end
                
                3'b110: //OR
                        begin
                            ALUctrl = 4'b1000;
                            RegWrite = 1;
                            ImmSrc = 3'b011;
                            ALUsrc = 0;
                            PCsrc = 2'b0;
                            ResultSrc = 0;
                            Data_WE = 0;
                            PCJump = 0;
                        end
                
                3'b111:
                        begin
                            ALUctrl = 4'b1001;
                            RegWrite = 1;
                            ImmSrc = 3'b011;
                            ALUsrc = 0;
                            PCsrc = 2'b0;
                            ResultSrc = 0;
                            Data_WE = 0;
                            PCJump = 0;
                        end
                   
                    
                default:
                    begin
                        ALUctrl = instr[14:12];
                        RegWrite = 0;
                        ImmSrc = 3'b0;
                        ALUsrc = 0;
                        PCsrc = 0;
                        ResultSrc = 0;
                        Data_WE = 0;
                        PCJump = 0;
                    end
                endcase


//I type instructions

    7'b0010011:
                begin //addi
                    ALUctrl = instr[14:12];
                    RegWrite = 1;
                    ImmSrc = 3'b0;
                    ALUsrc = 1;
                    PCsrc = 2'b0;
                    ResultSrc = 0;
                    Data_WE = 0;
                end

//I-type, loading instructions
    7'b0000011: 
                case(funct3)

                3'b010:
                    begin  //load word (lw)
                        ALUctrl = instr[14:12];
                        RegWrite = 1;
                        ImmSrc = 3'b0;
                        ALUsrc = 1;
                        PCsrc = 2'b0;
                        ResultSrc = 1;
                        PCJump = 0;
                        Data_WE = 0;
                    end
                3'b001:
                    begin //load half (lh)
                        ALUctrl = instr[14:12];
                        RegWrite = 1;
                        ImmSrc = 3'b0;
                        ALUsrc = 1;
                        PCsrc = 2'b0;
                        ResultSrc = 1;
                        PCJump = 0;
                        Data_WE = 0;
                    end
                3'b000: //load byte (lb)
                    begin
                        ALUctrl = instr[14:12];
                        RegWrite = 1;
                        ImmSrc = 3'b0;
                        ALUsrc = 1;
                        PCsrc = 2'b0;
                        ResultSrc = 1;
                        PCJump = 0;
                        Data_WE = 0;
                    end
                endcase

// S type instructions
    7'b0100011:
                case(funct3)

                3'b010:
                    begin //store word (sw)
                        ALUctrl = instr[14:12];
                        RegWrite = 0;
                        ImmSrc = 3'b01;
                        ALUsrc = 1;
                        PCsrc = 0;
                        Data_WE = 1;
                        ResultSrc = 1;
                        PCJump = 0;

                    
                    end
                3'b001: //store half (sh)
                    begin
                        ALUctrl = instr[14:12];
                        RegWrite = 0;
                        ImmSrc = 3'b01;
                        ALUsrc = 1;
                        PCsrc = 0;
                        Data_WE = 1;
                        ResultSrc = 1;
                        PCJump = 0;
                    end
                3'b000: //store byte (sb)
                    begin
                        ALUctrl = instr[14:12];
                        RegWrite = 0;
                        ImmSrc = 3'b01;
                        ALUsrc = 1;
                        PCsrc = 0;
                        Data_WE = 1;
                        ResultSrc = 1;
                        PCJump = 0;
                    end
                    
                endcase

                
//B type instructions

    7'b1100011: if (funct3 == 3'b1)
                    begin //bne
                        ALUctrl = instr[14:12];
                        RegWrite = 0;
                        PCsrc = {0, ~EQ};   
                        ImmSrc = 3'b10;
                        ALUsrc = 0;
                        ResultSrc = 0;
                        PCJump = 0;
                    end
                else if (funct3 == 3'b0)
                    begin //beq
                        ALUctrl = instr[14:12];
                        RegWrite = 0;
                        PCsrc = {0,~EQ};   
                        ImmSrc = 3'b10;
                        ALUsrc = 0;
                        ResultSrc = 0;
                        PCJump = 0;
                    end


    7'b1101111: //jal
                begin
                    ALUctrl = instr[14:12];
                    RegWrite = 1;
                    ImmSrc = 3'b101;
                    ALUsrc = 1;
                    PCsrc = 2'b10;
                    ResultSrc = 0;
                    PCJump = 1;
    end

    7'b1100111: //jalr
                begin
                    ALUctrl = instr[14:12];
                    RegWrite = 1; 
                    ImmSrc = 3'b101;
                    ALUsrc = 1;
                    PCsrc = 2'b11;
                    ResultSrc = 0;
                    PCJump = 1;
    end
    



    default:begin
    ALUctrl = instr[14:12];
    ImmSrc = 2'b00;
    PCsrc = 0;
    RegWrite = 0;
    ALUsrc = 0;
    ResultSrc = 0;
    Data_WE = 0;
    end

endcase



endmodule

    // Immsrc 00 for lw and addi, 01 for sw, 10 for bne 




    // begin                        // add      0110011
    // PCsrc = instr[6];            //addi      0010011
    // ALUsrc = ~instr[6];           //branch    1100011
    // ALUctrl = instr[14:12];      //          ||^ PCsrc
    // RegWrite = ~instr[6];        //          |^   not ALUsrc
    // ImmSrc = instr[6];          //          ^ not RegWrite 
    // end                          //          ALUctrl: funct3


    //ALU decoder

instr_rom.sv
module instr_rom 
// #(
//     parameter ADDRESS_WIDTH = 32, //should be in the same length as PC
//               DATA_WIDTH    = 8)
(
    input logic  [31:0]     addr,
    output logic [31:0]     dout

);

logic [7:0] rom_array [32'hBFC00000:32'hBFC00FFF]; 
//Theoretically, there should be 2^32 in memmory                // but we do not need that many space, so I made to 
                                            // have only 256 memory spaces
//date width should be 8bit because it is a byte addressable memory
//so each instruction consist of four 8-bit byte

initial begin
        $display("Loading Instr_mem.");
        $readmemh("instruction.mem", rom_array);  //read instruction into rom
        // $display(rom_array [0], rom_array [1], rom_array [2],rom_array [3]);
end;

always_comb
    dout <= {rom_array [addr[7:0]+3], rom_array [addr[7:0]+2], rom_array [addr[7:0]+1],rom_array [addr[7:0]]};
    // dout <= 8'h11;

endmodule

counter_unit.sv
module counter_unit #(
    parameter PC_WIDTH = 32 // the length of pc and imme
)(
    input  logic                clk,
    input  logic                rst,
    input  logic [1:0]          PCsrc,
    input  logic [PC_WIDTH-1:0] ImmOp,
    input  logic [PC_WIDTH-1:0] RD1,
    output logic [PC_WIDTH-1:0] PC
);

// logic [PC_WIDTH-1:0] next_PC;
// logic [PC_WIDTH-1:0] branch_PC;

// assign branch_PC = PC + ImmOp;                                        //compute branch_pc
// assign next_PC = PCsrc ? branch_PC : PC + {{PC_WIDTH-1{1'b0}}, 1'b1};    //compute inc_PC

always_ff @ (posedge clk)begin
  if (rst)           PC <= {PC_WIDTH{1'b0}};
  // else PC <= PCsrc[0] ? PC + ImmOp : PC + 4;
  else case(PCsrc)
          2'b00: PC <= PC  + 4;        //normal
          2'b01: PC <= PC  + ImmOp;    //branch or jal
          2'b10: PC <= PC  + 4;        //normal
          2'b11: PC <= RD1 + ImmOp;   //jalr
  endcase
end


endmodule

top.sv
module top #(
    parameter D_WIDTH = 32,
              A_WIDTH = 5
)(
    input  logic        clk,
    input  logic        rst,
    output logic [16:0] a0
);

logic [D_WIDTH-1:0] PC;
logic [D_WIDTH-1:0] ImmOp;
logic [1:0]         PCsrc;
logic               EQ;
logic               RegWrite;
logic               ALUctrl;
logic               ALUsrc;
logic               ResultSrc;
logic [1:0]         ImmSrc;
logic [A_WIDTH-1:0] AD1;
logic [A_WIDTH-1:0] AD2;
logic [A_WIDTH-1:0] AD3;
logic [D_WIDTH-1:0] RD1;
logic [D_WIDTH-1:0] RD2;
logic [D_WIDTH-1:0] ALUout;
logic [D_WIDTH-1:0] instr;
logic [D_WIDTH-1:0] out;
logic               PCJump;
logic               Data_WE;
logic [D_WIDTH-1:0] Data_addr;
logic [D_WIDTH-1:0] Data_RD;



counter_unit pc_counter(
    .clk(clk),
    .rst(rst),
    .PCsrc(PCsrc),
    .ImmOp(ImmOp),
    .RD1(Rd1),
    .PC(PC)
);

instr_rom instr_mem(
    .addr(PC),
    .dout(instr)
);

control_unit encoder(
    .EQ(EQ),
    .instr(instr),
    .RegWrite(RegWrite),
    .ALUsrc(ALUsrc),
    .PCsrc(PCsrc),
    .ALUctrl(ALUctrl),
    .ImmSrc(ImmSrc),
    .ResultSrc(ResultSrc),
    .Data_WE(Data_WE),
    .PCJump(PCJump)
);

RegFile register_file(
    .clk(clk),
    .WE3(RegWrite),
    .AD1(instr[19:15]),
    .AD2(instr[24:20]),
    .AD3(instr[11:7]),
    .RD1(RD1),
    .RD2(RD2),
    .ALUout(ALUout),
    .Data_RD(Data_RD),
    .ResultSrc(ResultSrc),
    .a0(a0),
    .PC(PC),
    .trigger(trigger),
    .PCJump(PCJump)
);

signextend extend(
    .instr(instr),
    .ImmSrc(ImmSrc),
    .ImmOp(ImmOp)
);

ALU_unit ALU(
    .ALUop1(RD1),
    .RegOp2(RD2),
    .ImmOp(ImmOp),
    .ALUctrl(ALUctrl),
    .ALUout(ALUout),
    .ALUsrc(ALUsrc),
    .EQ(EQ)
);

data_ram data_mem(
    .clk(clk),
    .Data_WE(Data_WE),
    .Data_addr(ALUout),
    .Data_RD(Data_RD),
    .Data_WD(RD2)
);



endmodule

top.vcd
$version Generated by VerilatedVcd $end
$date Wed Dec  7 22:27:50 2022 $end
$timescale 1ps $end

 $scope module TOP $end
  $var wire 17 c a0 [16:0] $end
  $var wire  1 a clk $end
  $var wire  1 b rst $end
  $scope module top $end
   $var wire  5 f AD1 [4:0] $end
   $var wire  5 g AD2 [4:0] $end
   $var wire  5 h AD3 [4:0] $end
   $var wire  1 & ALUctrl $end
   $var wire 32 ^ ALUout [31:0] $end
   $var wire  1 ' ALUsrc $end
   $var wire 32 e A_WIDTH [31:0] $end
   $var wire 32 d D_WIDTH [31:0] $end
   $var wire 32 7 Data_RD [31:0] $end
   $var wire  1 , Data_WE $end
   $var wire 32 j Data_addr [31:0] $end
   $var wire  1 [ EQ $end
   $var wire 32 $ ImmOp [31:0] $end
   $var wire  2 ) ImmSrc [1:0] $end
   $var wire 32 # PC [31:0] $end
   $var wire  1 + PCJump $end
   $var wire  2 Z PCsrc [1:0] $end
   $var wire 32 \ RD1 [31:0] $end
   $var wire 32 ] RD2 [31:0] $end
   $var wire  1 k Rd1 $end
   $var wire  1 % RegWrite $end
   $var wire  1 ( ResultSrc $end
   $var wire 17 c a0 [16:0] $end
   $var wire  1 a clk $end
   $var wire 32 * instr [31:0] $end
   $var wire 32 i out [31:0] $end
   $var wire  1 b rst $end
   $var wire  1 l trigger $end
   $scope module ALU $end
    $var wire  4 - ALUctrl [3:0] $end
    $var wire 32 \ ALUop1 [31:0] $end
    $var wire 32 _ ALUop2 [31:0] $end
    $var wire 32 ^ ALUout [31:0] $end
    $var wire  1 ' ALUsrc $end
    $var wire  1 [ EQ $end
    $var wire 32 $ ImmOp [31:0] $end
    $var wire 32 ] RegOp2 [31:0] $end
    $var wire 32 d WIDTH [31:0] $end
   $upscope $end
   $scope module data_mem $end
    $var wire 32 7 Data_RD [31:0] $end
    $var wire 32 ] Data_WD [31:0] $end
    $var wire  1 , Data_WE $end
    $var wire 32 ^ Data_addr [31:0] $end
    $var wire 32 d WIDTH [31:0] $end
    $var wire  1 a clk $end
   $upscope $end
   $scope module encoder $end
    $var wire  3 . ALUctrl [2:0] $end
    $var wire  1 ' ALUsrc $end
    $var wire  1 , Data_WE $end
    $var wire  1 [ EQ $end
    $var wire  3 / ImmSrc [2:0] $end
    $var wire  1 + PCJump $end
    $var wire  2 Z PCsrc [1:0] $end
    $var wire  1 % RegWrite $end
    $var wire  1 ( ResultSrc $end
    $var wire 32 d Width [31:0] $end
    $var wire  3 0 funct3 [2:0] $end
    $var wire  7 1 funct7 [6:0] $end
    $var wire 32 * instr [31:0] $end
    $var wire  7 2 opcode [6:0] $end
   $upscope $end
   $scope module extend $end
    $var wire 32 $ ImmOp [31:0] $end
    $var wire  3 3 ImmSrc [2:0] $end
    $var wire 32 d Width [31:0] $end
    $var wire 32 * instr [31:0] $end
   $upscope $end
   $scope module instr_mem $end
    $var wire 32 # addr [31:0] $end
    $var wire 32 * dout [31:0] $end
   $upscope $end
   $scope module pc_counter $end
    $var wire 32 $ ImmOp [31:0] $end
    $var wire 32 # PC [31:0] $end
    $var wire 32 d PC_WIDTH [31:0] $end
    $var wire  2 Z PCsrc [1:0] $end
    $var wire 32 m RD1 [31:0] $end
    $var wire  1 a clk $end
    $var wire  1 b rst $end
   $upscope $end
   $scope module register_file $end
    $var wire  5 4 AD1 [4:0] $end
    $var wire  5 5 AD2 [4:0] $end
    $var wire  5 6 AD3 [4:0] $end
    $var wire 32 ^ ALUout [31:0] $end
    $var wire 32 e A_WIDTH [31:0] $end
    $var wire 32 d D_WIDTH [31:0] $end
    $var wire 32 7 Data_RD [31:0] $end
    $var wire 32 # PC [31:0] $end
    $var wire  1 + PCJump $end
    $var wire 32 \ RD1 [31:0] $end
    $var wire 32 ] RD2 [31:0] $end
    $var wire  1 ( ResultSrc $end
    $var wire 32 X WD3 [31:0] $end
    $var wire  1 % WE3 $end
    $var wire 32 ` a0 [31:0] $end
    $var wire  1 a clk $end
    $var wire 32 8 reg_file[0] [31:0] $end
    $var wire 32 B reg_file[10] [31:0] $end
    $var wire 32 C reg_file[11] [31:0] $end
    $var wire 32 D reg_file[12] [31:0] $end
    $var wire 32 E reg_file[13] [31:0] $end
    $var wire 32 F reg_file[14] [31:0] $end
    $var wire 32 G reg_file[15] [31:0] $end
    $var wire 32 H reg_file[16] [31:0] $end
    $var wire 32 I reg_file[17] [31:0] $end
    $var wire 32 J reg_file[18] [31:0] $end
    $var wire 32 K reg_file[19] [31:0] $end
    $var wire 32 9 reg_file[1] [31:0] $end
    $var wire 32 L reg_file[20] [31:0] $end
    $var wire 32 M reg_file[21] [31:0] $end
    $var wire 32 N reg_file[22] [31:0] $end
    $var wire 32 O reg_file[23] [31:0] $end
    $var wire 32 P reg_file[24] [31:0] $end
    $var wire 32 Q reg_file[25] [31:0] $end
    $var wire 32 R reg_file[26] [31:0] $end
    $var wire 32 S reg_file[27] [31:0] $end
    $var wire 32 T reg_file[28] [31:0] $end
    $var wire 32 U reg_file[29] [31:0] $end
    $var wire 32 : reg_file[2] [31:0] $end
    $var wire 32 V reg_file[30] [31:0] $end
    $var wire 32 W reg_file[31] [31:0] $end
    $var wire 32 ; reg_file[3] [31:0] $end
    $var wire 32 < reg_file[4] [31:0] $end
    $var wire 32 = reg_file[5] [31:0] $end
    $var wire 32 > reg_file[6] [31:0] $end
    $var wire 32 ? reg_file[7] [31:0] $end
    $var wire 32 @ reg_file[8] [31:0] $end
    $var wire 32 A reg_file[9] [31:0] $end
    $var wire 32 Y result [31:0] $end
    $var wire  1 l trigger $end
   $upscope $end
  $upscope $end
 $upscope $end
$enddefinitions $end


#0
b00000000000000000000000000000000 #
b00000000000000000000000000000000 $
0%
0&
0'
0(
b00 )
b00000000000000000000000000000000 *
0+
0,
b0000 -
b000 .
b000 /
b000 0
b0000000 1
b0000000 2
b000 3
b00000 4
b00000 5
b00000 6
b00000000000000000000000000000000 7
b00000000000000000000000000000000 8
b00000000000000000000000000000000 9
b00000000000000000000000000000000 :
b00000000000000000000000000000000 ;
b00000000000000000000000000000000 <
b00000000000000000000000000000000 =
b00000000000000000000000000000000 >
b00000000000000000000000000000000 ?
b00000000000000000000000000000000 @
b00000000000000000000000000000000 A
b00000000000000000000000000000000 B
b00000000000000000000000000000000 C
b00000000000000000000000000000000 D
b00000000000000000000000000000000 E
b00000000000000000000000000000000 F
b00000000000000000000000000000000 G
b00000000000000000000000000000000 H
b00000000000000000000000000000000 I
b00000000000000000000000000000000 J
b00000000000000000000000000000000 K
b00000000000000000000000000000000 L
b00000000000000000000000000000000 M
b00000000000000000000000000000000 N
b00000000000000000000000000000000 O
b00000000000000000000000000000000 P
b00000000000000000000000000000000 Q
b00000000000000000000000000000000 R
b00000000000000000000000000000000 S
b00000000000000000000000000000000 T
b00000000000000000000000000000000 U
b00000000000000000000000000000000 V
b00000000000000000000000000000000 W
b00000000000000000000000000000000 X
b00000000000000000000000000000000 Y
b00 Z
0[
b00000000000000000000000000000000 \
b00000000000000000000000000000000 ]
b00000000000000000000000000000000 ^
b00000000000000000000000000000000 _
b00000000000000000000000000000000 `
0a
0b
b00000000000000000 c
b00000000000000000000000000100000 d
b00000000000000000000000000000101 e
b00000 f
b00000 g
b00000 h
b00000000000000000000000000000000 i
b00000000000000000000000000000000 j
0k
0l
b00000000000000000000000000000000 m
#1
b11111110000000000000000000000000 7
1[
1a
#2
0a
1b
#3
1a
#4
0a
0b
#5
b00000000000000000000000000000100 #
1a
#6
0a
#7
b00000000000000000000000000001000 #
1a
#8
0a
#9
b00000000000000000000000000001100 #
1a
#10
0a
#11
b00000000000000000000000000010000 #
1a
#12
0a
#13
b00000000000000000000000000010100 #
1a
#14
0a
#15
b00000000000000000000000000011000 #
1a
#16
0a
#17
b00000000000000000000000000011100 #
1a
#18
0a
#19
b00000000000000000000000000100000 #
1a
#20
0a
#21
b00000000000000000000000000100100 #
1a
#22
0a
#23
b00000000000000000000000000101000 #
1a
#24
0a
#25
b00000000000000000000000000101100 #
1a
#26
0a
#27
b00000000000000000000000000110000 #
1a
#28
0a
#29
b00000000000000000000000000110100 #
1a
#30
0a
#31
b00000000000000000000000000111000 #
1a
#32
0a
#33
b00000000000000000000000000111100 #
1a
#34
0a
#35
b00000000000000000000000001000000 #
1a
#36
0a
#37
b00000000000000000000000001000100 #
1a
#38
0a
#39
b00000000000000000000000001001000 #
1a
#40
0a
#41
b00000000000000000000000001001100 #
1a
#42
0a
#43
b00000000000000000000000001010000 #
1a
#44
0a
#45
b00000000000000000000000001010100 #
1a
#46
0a
#47
b00000000000000000000000001011000 #
1a
#48
0a
#49
b00000000000000000000000001011100 #
1a
#50
0a
#51
b00000000000000000000000001100000 #
1a
#52
0a
#53
b00000000000000000000000001100100 #
1a
#54
0a
#55
b00000000000000000000000001101000 #
1a
#56
0a
#57
b00000000000000000000000001101100 #
1a
#58
0a
#59
b00000000000000000000000001110000 #
1a
#60
0a
#61
b00000000000000000000000001110100 #
1a
#62
0a
#63
b00000000000000000000000001111000 #
1a
#64
0a
#65
b00000000000000000000000001111100 #
1a
#66
0a
#67
b00000000000000000000000010000000 #
1a
#68
0a
#69
b00000000000000000000000010000100 #
1a
#70
0a
#71
b00000000000000000000000010001000 #
1a
#72
0a
#73
b00000000000000000000000010001100 #
1a
#74
0a
#75
b00000000000000000000000010010000 #
1a
#76
0a
#77
b00000000000000000000000010010100 #
1a
#78
0a
#79
b00000000000000000000000010011000 #
1a
#80
0a
#81
b00000000000000000000000010011100 #
1a
#82
0a
#83
b00000000000000000000000010100000 #
1a
#84
0a
#85
b00000000000000000000000010100100 #
1a
#86
0a
#87
b00000000000000000000000010101000 #
1a
#88
0a
#89
b00000000000000000000000010101100 #
1a
#90
0a
#91
b00000000000000000000000010110000 #
1a
#92
0a
#93
b00000000000000000000000010110100 #
1a
#94
0a
#95
b00000000000000000000000010111000 #
1a
#96
0a
#97
b00000000000000000000000010111100 #
1a
#98
0a
#99
b00000000000000000000000011000000 #
1a
#100
0a
#101
b00000000000000000000000011000100 #
1a
#102
0a
#103
b00000000000000000000000011001000 #
1a
#104
0a
#105
b00000000000000000000000011001100 #
1a
#106
0a
#107
b00000000000000000000000011010000 #
1a
#108
0a
#109
b00000000000000000000000011010100 #
1a
#110
0a
#111
b00000000000000000000000011011000 #
1a
#112
0a
#113
b00000000000000000000000011011100 #
1a
#114
0a
#115
b00000000000000000000000011100000 #
1a
#116
0a
#117
b00000000000000000000000011100100 #
1a
#118
0a
#119
b00000000000000000000000011101000 #
1a
#120
0a
#121
b00000000000000000000000011101100 #
1a
#122
0a
#123
b00000000000000000000000011110000 #
1a
#124
0a
#125
b00000000000000000000000011110100 #
1a
#126
0a
#127
b00000000000000000000000011111000 #
1a
#128
0a
#129
b00000000000000000000000011111100 #
1a
#130
0a
#131
b00000000000000000000000100000000 #
1a
#132
0a
#133
b00000000000000000000000100000100 #
1a
#134
0a
#135
b00000000000000000000000100001000 #
1a
#136
0a
#137
b00000000000000000000000100001100 #
1a
#138
0a
#139
b00000000000000000000000100010000 #
1a
#140
0a
#141
b00000000000000000000000100010100 #
1a
#142
0a
#143
b00000000000000000000000100011000 #
1a
#144
0a
#145
b00000000000000000000000100011100 #
1a
#146
0a
#147
b00000000000000000000000100100000 #
1a
#148
0a
#149
b00000000000000000000000100100100 #
1a
#150
0a
#151
b00000000000000000000000100101000 #
1a
#152
0a
#153
b00000000000000000000000100101100 #
1a
#154
0a
#155
b00000000000000000000000100110000 #
1a
#156
0a
#157
b00000000000000000000000100110100 #
1a
#158
0a
#159
b00000000000000000000000100111000 #
1a
#160
0a
#161
b00000000000000000000000100111100 #
1a
#162
0a
#163
b00000000000000000000000101000000 #
1a
#164
0a
#165
b00000000000000000000000101000100 #
1a
#166
0a
#167
b00000000000000000000000101001000 #
1a
#168
0a
#169
b00000000000000000000000101001100 #
1a
#170
0a
#171
b00000000000000000000000101010000 #
1a
#172
0a
#173
b00000000000000000000000101010100 #
1a
#174
0a
#175
b00000000000000000000000101011000 #
1a
#176
0a
#177
b00000000000000000000000101011100 #
1a
#178
0a
#179
b00000000000000000000000101100000 #
1a
#180
0a
#181
b00000000000000000000000101100100 #
1a
#182
0a
#183
b00000000000000000000000101101000 #
1a
#184
0a
#185
b00000000000000000000000101101100 #
1a
#186
0a
#187
b00000000000000000000000101110000 #
1a
#188
0a
#189
b00000000000000000000000101110100 #
1a
#190
0a
#191
b00000000000000000000000101111000 #
1a
#192
0a
#193
b00000000000000000000000101111100 #
1a
#194
0a
#195
b00000000000000000000000110000000 #
1a
#196
0a
#197
b00000000000000000000000110000100 #
1a
#198
0a
#199
b00000000000000000000000110001000 #
1a
#200
0a
#201
b00000000000000000000000110001100 #
1a
#202
0a
#203
b00000000000000000000000110010000 #
1a
#204
0a
#205
b00000000000000000000000110010100 #
1a
#206
0a
#207
b00000000000000000000000110011000 #
1a
#208
0a
#209
b00000000000000000000000110011100 #
1a
#210
0a
#211
b00000000000000000000000110100000 #
1a
#212
0a
#213
b00000000000000000000000110100100 #
1a
#214
0a
#215
b00000000000000000000000110101000 #
1a
#216
0a
#217
b00000000000000000000000110101100 #
1a
#218
0a
#219
b00000000000000000000000110110000 #
1a
#220
0a
#221
b00000000000000000000000110110100 #
1a
#222
0a
#223
b00000000000000000000000110111000 #
1a
#224
0a
#225
b00000000000000000000000110111100 #
1a
#226
0a
#227
b00000000000000000000000111000000 #
1a
#228
0a
#229
b00000000000000000000000111000100 #
1a
#230
0a
#231
b00000000000000000000000111001000 #
1a
#232
0a
#233
b00000000000000000000000111001100 #
1a
#234
0a
#235
b00000000000000000000000111010000 #
1a
#236
0a
#237
b00000000000000000000000111010100 #
1a
#238
0a
#239
b00000000000000000000000111011000 #
1a
#240
0a
#241
b00000000000000000000000111011100 #
1a
#242
0a
#243
b00000000000000000000000111100000 #
1a
#244
0a
#245
b00000000000000000000000111100100 #
1a
#246
0a
#247
b00000000000000000000000111101000 #
1a
#248
0a
#249
b00000000000000000000000111101100 #
1a
#250
0a
#251
b00000000000000000000000111110000 #
1a
#252
0a
#253
b00000000000000000000000111110100 #
1a
#254
0a
#255
b00000000000000000000000111111000 #
1a
