data_ram.sv
module data_ram #(
    parameter WIDTH = 32
)(
    input logic                clk,
    input logic                Data_WE,
    input logic  [WIDTH -1:0]  Data_addr,
    input logic [WIDTH -1:0]   Data_WD,
    output logic  [WIDTH -1:0] Data_RD
);


logic [7:0] data_mem [32'h00001FFF:32'h00001000];

initial begin
        $display("Loading Data_mem.");
        $readmemh("data.mem", data_mem);
end;

always_comb begin
    Data_RD = {data_mem[Data_addr+3], data_mem[Data_addr+2], data_mem[Data_addr+1], data_mem[Data_addr]};
end

always_ff @(posedge clk)
    if (Data_WE) begin
    data_mem[Data_addr+3] = Data_WD[31:24];
    data_mem[Data_addr+2] = Data_WD[23:16];
    data_mem[Data_addr+1] = Data_WD[15:8];
    data_mem[Data_addr] = Data_WD[7:0];
    end

endmodule

ALU_unit.sv
module ALU_unit #(
    parameter WIDTH = 32
)(
    input   logic [WIDTH-1:0] ALUop1,
    input   logic [WIDTH-1:0] RegOp2,
    input   logic [WIDTH-1:0] ImmOp,
    output  logic [WIDTH-1:0] ALUout,
    input   logic [3:0]       ALUctrl,
    input   logic             ALUsrc,
    output  logic             EQ
);

logic [WIDTH-1:0] ALUop2;

always_comb begin
    ALUop2 = ALUsrc ? ImmOp : RegOp2; 
    case (ALUctrl)
        4'b0000: ALUout = ALUop1 + ALUop2;
        4'b0001: ALUout = ALUop1 - ALUop2;
        4'b0010: ALUout = ALUop1 << ALUop2[4:0];
        4'b0011: 
            if ( ~ALUop1[31] & ~ ALUop2[31])
                ALUout <= (ALUop1[30:0] < ALUop2[30:0]);
            else if (ALUop1[31] & ~ ALUop2[31])
                ALUout <= 32'b1;
            else if (~ALUop1[31] & ALUop2[31])
                ALUout <= 32'b0;
            else
                ALUout <= (ALUop1[30:0] > ALUop2[30:0]);
        4'b0100: ALUout = (ALUop1 < ALUop2);
        4'b0101: ALUout = ALUop1 | ALUop2;
        4'b0110: ALUout = ALUop1 >> ALUop2[4:0];
        4'b0111: ALUout = ALUop1 >>> ALUop2[4:0];
        4'b1000: ALUout = ALUop1 | ALUop2;
        4'b1001: ALUout = ALUop1 & ALUop2;
    endcase
    EQ = (ALUop1 == ALUop2);
end
endmodule

signextend.sv
module signextend #(
    parameter Width = 32
)(
    input  logic [Width-1:0] instr,
    input  logic [2:0]       ImmSrc,
    output logic [Width-1:0] ImmOp
);


// assign ImmOp = ImmSrc ? { {20{instr[31]}}, instr[31:20] } : { {20{instr[31]}}, instr[31], instr[7], instr[30:25], instr[11:8], 1'b0 };  

always_comb

    case(ImmSrc)

    3'b000:    ImmOp = { {20{instr[31]}}, instr[31:20] }; //I-type
    3'b001:    ImmOp = { {20{instr[31]}}, instr[31:25], instr[11:7] }; //S-type
    3'b010:    ImmOp = { {19{instr[31]}}, instr[31], instr[7], instr[30:25], instr[11:8], 1'b0 }; //B-type
    3'b011:    ImmOp = {32'b0}; //R-Type (has no immediate)
    3'b100:    ImmOp = { {12{instr[31]}}, instr[31:12] }; // U-Type
    3'b101:    ImmOp = { {11{instr[31]}}, instr[31], instr[19:12], instr[20], instr[30:21], 1'b0 };  // J-type
    //3'b110: zero extension tbi
    //3'b111:  unsigned extension tbi 
    default:   ImmOp = { {20{instr[31]}}, instr[31:20] }; //default I type

    
    endcase



endmodule

RegFile.sv
module RegFile #(
    parameter D_WIDTH = 32,
              A_WIDTH = 5
)(
    input  logic                clk,
    input  logic                WE3,
    input  logic                ResultSrc,
    input  logic                PCJump,
    input  logic                trigger,
    input  logic [D_WIDTH-1:0]  PC,
    input  logic [A_WIDTH-1:0]  AD1,
    input  logic [A_WIDTH-1:0]  AD2,
    input  logic [A_WIDTH-1:0]  AD3,
    input  logic [D_WIDTH-1:0]  ALUout,
    input  logic [D_WIDTH-1:0]  Data_RD,
    output logic [D_WIDTH-1:0]  RD1,
    output logic [D_WIDTH-1:0]  RD2,
    output logic [D_WIDTH-1:0]  a0
);

reg [D_WIDTH-1:0] reg_file [31:0];

logic [D_WIDTH-1:0] WD3;
logic [D_WIDTH-1:0] result;

assign WD3 = PCJump ? PC + 4 : result;
assign result = ResultSrc ? Data_RD : ALUout;

// initial begin
//     // for (i = 0; i < 2**A_WIDTH -1; i++){
//     //     reg_file[i] <= 32'b0
//     // }
//     $display("Loading RegFile.");
//     $readmemh("RegFile.mem", reg_file);
// end;
assign reg_file[0] = 32'b0;

always_ff @( posedge clk ) begin 

    if (WE3) reg_file[AD3] = WD3;
    
end

always_comb begin
    RD1 = reg_file[AD1];
    RD2 = reg_file[AD2];
    a0 <= reg_file[10];
    reg_file[5] <= trigger;
end

endmodule

control_unit.sv
module control_unit #(
    parameter Width = 32
)(
    input  logic           EQ,
    input  logic [Width-1:0] instr,
    output logic           RegWrite,
    output logic           ResultSrc,
    output logic           ALUsrc,
    output logic [1:0]     PCsrc,
    output logic [3:0]     ALUctrl,
    output logic [2:0]     ImmSrc,
    output logic           Data_WE,
    output logic           PCJump

);

logic [2:0] funct3;
logic [6:0] funct7;
logic [6:0] opcode;

assign funct3 = instr[14:12];
assign funct7 = instr[31:25];
assign opcode = instr[6:0];


always_comb

case(opcode)

//R-type instructions
     7'b0110011: 
                case(funct3)
            
                3'b000: begin 
                    if (funct7 == 7'b0) //add 
                        begin
                            ALUctrl = 4'b0000;
                            RegWrite = 1;
                            ImmSrc = 3'b011;
                            ALUsrc = 0;
                            PCsrc = 2'b0;
                            ResultSrc = 0;
                            Data_WE = 0;
                            PCJump = 0;
                        end
                    else //sub
                        begin
                            ALUctrl = 4'b0001;
                            RegWrite = 1;
                            ImmSrc = 3'b011;
                            ALUsrc = 0;
                            PCsrc = 2'b0;
                            ResultSrc = 0;
                            Data_WE = 0;
                            PCJump = 0;
                        end    end                 
                            

                3'b001: //shift left logical (sll)
                    begin
                        ALUctrl = 4'b0010;
                        RegWrite = 1;
                        ImmSrc = 3'b011;
                        ALUsrc = 0;
                        PCsrc = 2'b0;
                        ResultSrc = 0;
                        Data_WE = 0;
                        PCJump = 0;
                    end

                3'b010: //set less than
                        begin
                            ALUctrl = 4'b0011;
                            RegWrite = 1;
                            ImmSrc = 3'b011;
                            ALUsrc = 0;
                            PCsrc = 2'b0;
                            ResultSrc = 0;
                            Data_WE = 0;
                            PCJump = 0;
                        end 
                
                3'b011: //set less than unsigned
                
                        begin
                            ALUctrl = 4'b0100;
                            RegWrite = 1;
                            ImmSrc = 3'b011;
                            ALUsrc = 0;
                            PCsrc = 2'b0;
                            ResultSrc = 0;
                            Data_WE = 0;
                            PCJump = 0;
                        end
                
                3'b100: //xor
                        begin
                            ALUctrl = 4'b0101;
                            RegWrite = 1;
                            ImmSrc = 3'b011;
                            ALUsrc = 0;
                            PCsrc = 2'b0;
                            ResultSrc = 0;
                            Data_WE = 0;
                            PCJump = 0;
                        end
                
                3'b101: 

                    if (funct7 == 7'b0) //shift right logical
                        begin
                            ALUctrl = 4'b0110;
                            RegWrite = 1;
                            ImmSrc = 3'b011;
                            ALUsrc = 0;
                            PCsrc = 2'b0;
                            ResultSrc = 0;
                            Data_WE = 0;
                            PCJump = 0;
                        end

                    else //shift right arithmetic
                        begin
                            ALUctrl = 4'b0111;
                            RegWrite = 1;
                            ImmSrc = 3'b011;
                            ALUsrc = 0;
                            PCsrc = 2'b0;
                            ResultSrc = 0;
                            Data_WE = 0;
                            PCJump = 0;
                        end
                
                3'b110: //OR
                        begin
                            ALUctrl = 4'b1000;
                            RegWrite = 1;
                            ImmSrc = 3'b011;
                            ALUsrc = 0;
                            PCsrc = 2'b0;
                            ResultSrc = 0;
                            Data_WE = 0;
                            PCJump = 0;
                        end
                
                3'b111:
                        begin
                            ALUctrl = 4'b1001;
                            RegWrite = 1;
                            ImmSrc = 3'b011;
                            ALUsrc = 0;
                            PCsrc = 2'b0;
                            ResultSrc = 0;
                            Data_WE = 0;
                            PCJump = 0;
                        end
                   
                    
                default:
                    begin
                        ALUctrl = 4'b0000;
                        RegWrite = 0;
                        ImmSrc = 3'b0;
                        ALUsrc = 0;
                        PCsrc = 0;
                        ResultSrc = 0;
                        Data_WE = 0;
                        PCJump = 0;
                    end
                endcase


//I type instructions

    7'b0010011: begin
        case(funct3)
            3'b000: ALUctrl = 4'b0000; //addi
            3'b001: ALUctrl = 4'b0010; //slli
        endcase
        RegWrite = 1;
        ImmSrc = 3'b0;
        ALUsrc = 1;
        PCsrc = 2'b0;
        ResultSrc = 0;
        Data_WE = 0;
        PCJump = 0;
    end

//I-type, loading instructions
    7'b0000011: 
                case(funct3)

                3'b010:
                    begin  //load word (lw)
                        ALUctrl = 4'b0000;
                        RegWrite = 1;
                        ImmSrc = 3'b0;
                        ALUsrc = 1;
                        PCsrc = 2'b0;
                        ResultSrc = 1;
                        PCJump = 0;
                        Data_WE = 0;
                    end
                3'b001:
                    begin //load half (lh)
                        ALUctrl = 4'b0000;
                        RegWrite = 1;
                        ImmSrc = 3'b0;
                        ALUsrc = 1;
                        PCsrc = 2'b0;
                        ResultSrc = 1;
                        PCJump = 0;
                        Data_WE = 0;
                    end
                3'b000: //load byte (lb)
                    begin
                        ALUctrl = 4'b0000;
                        RegWrite = 1;
                        ImmSrc = 3'b0;
                        ALUsrc = 1;
                        PCsrc = 2'b0;
                        ResultSrc = 1;
                        PCJump = 0;
                        Data_WE = 0;
                    end
                endcase

// S type instructions
    7'b0100011:
                case(funct3)

                3'b010:
                    begin //store word (sw)
                        ALUctrl = 4'b0000;
                        RegWrite = 0;
                        ImmSrc = 3'b01;
                        ALUsrc = 1;
                        PCsrc = 0;
                        Data_WE = 1;
                        ResultSrc = 1;
                        PCJump = 0;

                    
                    end
                3'b001: //store half (sh)
                    begin
                        ALUctrl = 4'b0000;
                        RegWrite = 0;
                        ImmSrc = 3'b01;
                        ALUsrc = 1;
                        PCsrc = 0;
                        Data_WE = 1;
                        ResultSrc = 1;
                        PCJump = 0;
                    end
                3'b000: //store byte (sb)
                    begin
                        ALUctrl = 4'b0000;
                        RegWrite = 0;
                        ImmSrc = 3'b01;
                        ALUsrc = 1;
                        PCsrc = 0;
                        Data_WE = 1;
                        ResultSrc = 1;
                        PCJump = 0;
                    end
                    
                endcase

                
//B type instructions

    7'b1100011: if (funct3 == 3'b1)
                    begin //bne
                        ALUctrl = 4'b0000;
                        RegWrite = 0;
                        PCsrc = {0, ~EQ};   
                        ImmSrc = 3'b10;
                        ALUsrc = 0;
                        ResultSrc = 0;
                        PCJump = 0;
                    end
                else if (funct3 == 3'b0)
                    begin //beq
                        ALUctrl = 4'b0000;
                        RegWrite = 0;
                        PCsrc = {0,EQ};   
                        ImmSrc = 3'b10;
                        ALUsrc = 0;
                        ResultSrc = 0;
                        PCJump = 0;
                    end


    7'b1101111: //jal
                begin
                    ALUctrl = 4'b0000;
                    RegWrite = 1;
                    ImmSrc = 3'b101;
                    ALUsrc = 1;
                    PCsrc = 2'b01;
                    ResultSrc = 0;
                    PCJump = 1;
    end

    7'b1100111: //jalr
                begin
                    ALUctrl = 4'b0000;
                    RegWrite = 1; 
                    ImmSrc = 3'b000;
                    ALUsrc = 1;
                    PCsrc = 2'b11;
                    ResultSrc = 0;
                    PCJump = 1;
    end
    



    default:begin
    ALUctrl = 4'b0000;
    ImmSrc = 2'b00;
    PCsrc = 0;
    RegWrite = 0;
    ALUsrc = 0;
    ResultSrc = 0;
    Data_WE = 0;
    end

endcase



endmodule

    // Immsrc 00 for lw and addi, 01 for sw, 10 for bne 




    // begin                        // add      0110011
    // PCsrc = instr[6];            //addi      0010011
    // ALUsrc = ~instr[6];           //branch    1100011
    // ALUctrl = instr[14:12];      //          ||^ PCsrc
    // RegWrite = ~instr[6];        //          |^   not ALUsrc
    // ImmSrc = instr[6];          //          ^ not RegWrite 
    // end                          //          ALUctrl: funct3


    //ALU decoder

instr_rom.sv
module instr_rom 
// #(
//     parameter ADDRESS_WIDTH = 32, //should be in the same length as PC
//               DATA_WIDTH    = 8)
(
    input logic  [31:0]     addr,
    output logic [31:0]     dout

);

logic [7:0] rom_array [32'hBFC00000:32'hBFC00FFF]; 
//Theoretically, there should be 2^32 in memmory                // but we do not need that many space, so I made to 
                                            // have only 256 memory spaces
//date width should be 8bit because it is a byte addressable memory
//so each instruction consist of four 8-bit byte

initial begin
        $display("Loading Instr_mem.");
        $readmemh("instruction.mem", rom_array);  //read instruction into rom
        // $display(rom_array [0], rom_array [1], rom_array [2],rom_array [3]);
end;

always_comb
    dout <= {rom_array [addr[7:0]+3], rom_array [addr[7:0]+2], rom_array [addr[7:0]+1],rom_array [addr[7:0]]};
    // dout <= 8'h11;

endmodule

counter_unit.sv
module counter_unit #(
    parameter PC_WIDTH = 32 // the length of pc and imme
)(
    input  logic                clk,
    input  logic                rst,
    input  logic [1:0]          PCsrc,
    input  logic [PC_WIDTH-1:0] ImmOp,
    input  logic [PC_WIDTH-1:0] RD1,
    output logic [PC_WIDTH-1:0] PC
);

// logic [PC_WIDTH-1:0] next_PC;
// logic [PC_WIDTH-1:0] branch_PC;

// assign branch_PC = PC + ImmOp;                                        //compute branch_pc
// assign next_PC = PCsrc ? branch_PC : PC + {{PC_WIDTH-1{1'b0}}, 1'b1};    //compute inc_PC

always_ff @ (posedge clk)begin
  if (rst)           PC <= {PC_WIDTH{32'hBFC00000}};
  // else PC <= PCsrc[0] ? PC + ImmOp : PC + 4;
  else case(PCsrc)
          2'b00: PC <= PC  + 4;        //normal
          2'b01: PC <= PC  + ImmOp;    //branch or jal
          2'b10: PC <= PC  + 4;        //normal
          2'b11: PC <= RD1 + ImmOp;   //jalr
  endcase
end


endmodule

top.sv
module top #(
    parameter D_WIDTH = 32,
              A_WIDTH = 5
)(
    input  logic        clk,
    input  logic        rst,
    input  logic        trigger,
    output logic [31:0] a0
);

logic [D_WIDTH-1:0] PC;
logic [D_WIDTH-1:0] ImmOp;
logic [1:0]         PCsrc;
logic               EQ;
logic               RegWrite;
logic [3:0]         ALUctrl;
logic               ALUsrc;
logic               ResultSrc;
logic [2:0]         ImmSrc;
logic [A_WIDTH-1:0] AD1;
logic [A_WIDTH-1:0] AD2;
logic [A_WIDTH-1:0] AD3;
logic [D_WIDTH-1:0] RD1;
logic [D_WIDTH-1:0] RD2;
logic [D_WIDTH-1:0] ALUout;
logic [D_WIDTH-1:0] instr;
logic [D_WIDTH-1:0] out;
logic               PCJump;
logic               Data_WE;
logic [D_WIDTH-1:0] Data_addr;
logic [D_WIDTH-1:0] Data_RD;



counter_unit pc_counter(
    .clk(clk),
    .rst(rst),
    .PCsrc(PCsrc),
    .ImmOp(ImmOp),
    .RD1(RD1),
    .PC(PC)
);

instr_rom instr_mem(
    .addr(PC),
    .dout(instr)
);

control_unit encoder(
    .EQ(EQ),
    .instr(instr),
    .RegWrite(RegWrite),
    .ALUsrc(ALUsrc),
    .PCsrc(PCsrc),
    .ALUctrl(ALUctrl),
    .ImmSrc(ImmSrc),
    .ResultSrc(ResultSrc),
    .Data_WE(Data_WE),
    .PCJump(PCJump)
);

RegFile register_file(
    .clk(clk),
    .WE3(RegWrite),
    .AD1(instr[19:15]),
    .AD2(instr[24:20]),
    .AD3(instr[11:7]),
    .RD1(RD1),
    .RD2(RD2),
    .ALUout(ALUout),
    .Data_RD(Data_RD),
    .ResultSrc(ResultSrc),
    .a0(a0),
    .PC(PC),
    .trigger(trigger),
    .PCJump(PCJump)
);

signextend extend(
    .instr(instr),
    .ImmSrc(ImmSrc),
    .ImmOp(ImmOp)
);

ALU_unit ALU(
    .ALUop1(RD1),
    .RegOp2(RD2),
    .ImmOp(ImmOp),
    .ALUctrl(ALUctrl),
    .ALUout(ALUout),
    .ALUsrc(ALUsrc),
    .EQ(EQ)
);

data_ram data_mem(
    .clk(clk),
    .Data_WE(Data_WE),
    .Data_addr(ALUout),
    .Data_RD(Data_RD),
    .Data_WD(RD2)
);



endmodule

top.vcd
$version Generated by VerilatedVcd $end
$date Thu Dec  8 13:16:38 2022 $end
$timescale 1ps $end

 $scope module TOP $end
  $var wire 32 _ a0 [31:0] $end
  $var wire  1 \ clk $end
  $var wire  1 ] rst $end
  $var wire  1 ^ trigger $end
  $scope module top $end
   $var wire  5 b AD1 [4:0] $end
   $var wire  5 c AD2 [4:0] $end
   $var wire  5 d AD3 [4:0] $end
   $var wire  4 & ALUctrl [3:0] $end
   $var wire 32 Z ALUout [31:0] $end
   $var wire  1 ' ALUsrc $end
   $var wire 32 a A_WIDTH [31:0] $end
   $var wire 32 ` D_WIDTH [31:0] $end
   $var wire 32 3 Data_RD [31:0] $end
   $var wire  1 , Data_WE $end
   $var wire 32 f Data_addr [31:0] $end
   $var wire  1 W EQ $end
   $var wire 32 $ ImmOp [31:0] $end
   $var wire  3 ) ImmSrc [2:0] $end
   $var wire 32 # PC [31:0] $end
   $var wire  1 + PCJump $end
   $var wire  2 V PCsrc [1:0] $end
   $var wire 32 X RD1 [31:0] $end
   $var wire 32 Y RD2 [31:0] $end
   $var wire  1 % RegWrite $end
   $var wire  1 ( ResultSrc $end
   $var wire 32 _ a0 [31:0] $end
   $var wire  1 \ clk $end
   $var wire 32 * instr [31:0] $end
   $var wire 32 e out [31:0] $end
   $var wire  1 ] rst $end
   $var wire  1 ^ trigger $end
   $scope module ALU $end
    $var wire  4 & ALUctrl [3:0] $end
    $var wire 32 X ALUop1 [31:0] $end
    $var wire 32 [ ALUop2 [31:0] $end
    $var wire 32 Z ALUout [31:0] $end
    $var wire  1 ' ALUsrc $end
    $var wire  1 W EQ $end
    $var wire 32 $ ImmOp [31:0] $end
    $var wire 32 Y RegOp2 [31:0] $end
    $var wire 32 ` WIDTH [31:0] $end
   $upscope $end
   $scope module data_mem $end
    $var wire 32 3 Data_RD [31:0] $end
    $var wire 32 Y Data_WD [31:0] $end
    $var wire  1 , Data_WE $end
    $var wire 32 Z Data_addr [31:0] $end
    $var wire 32 ` WIDTH [31:0] $end
    $var wire  1 \ clk $end
   $upscope $end
   $scope module encoder $end
    $var wire  4 & ALUctrl [3:0] $end
    $var wire  1 ' ALUsrc $end
    $var wire  1 , Data_WE $end
    $var wire  1 W EQ $end
    $var wire  3 ) ImmSrc [2:0] $end
    $var wire  1 + PCJump $end
    $var wire  2 V PCsrc [1:0] $end
    $var wire  1 % RegWrite $end
    $var wire  1 ( ResultSrc $end
    $var wire 32 ` Width [31:0] $end
    $var wire  3 - funct3 [2:0] $end
    $var wire  7 . funct7 [6:0] $end
    $var wire 32 * instr [31:0] $end
    $var wire  7 / opcode [6:0] $end
   $upscope $end
   $scope module extend $end
    $var wire 32 $ ImmOp [31:0] $end
    $var wire  3 ) ImmSrc [2:0] $end
    $var wire 32 ` Width [31:0] $end
    $var wire 32 * instr [31:0] $end
   $upscope $end
   $scope module instr_mem $end
    $var wire 32 # addr [31:0] $end
    $var wire 32 * dout [31:0] $end
   $upscope $end
   $scope module pc_counter $end
    $var wire 32 $ ImmOp [31:0] $end
    $var wire 32 # PC [31:0] $end
    $var wire 32 ` PC_WIDTH [31:0] $end
    $var wire  2 V PCsrc [1:0] $end
    $var wire 32 X RD1 [31:0] $end
    $var wire  1 \ clk $end
    $var wire  1 ] rst $end
   $upscope $end
   $scope module register_file $end
    $var wire  5 0 AD1 [4:0] $end
    $var wire  5 1 AD2 [4:0] $end
    $var wire  5 2 AD3 [4:0] $end
    $var wire 32 Z ALUout [31:0] $end
    $var wire 32 a A_WIDTH [31:0] $end
    $var wire 32 ` D_WIDTH [31:0] $end
    $var wire 32 3 Data_RD [31:0] $end
    $var wire 32 # PC [31:0] $end
    $var wire  1 + PCJump $end
    $var wire 32 X RD1 [31:0] $end
    $var wire 32 Y RD2 [31:0] $end
    $var wire  1 ( ResultSrc $end
    $var wire 32 T WD3 [31:0] $end
    $var wire  1 % WE3 $end
    $var wire 32 _ a0 [31:0] $end
    $var wire  1 \ clk $end
    $var wire 32 4 reg_file[0] [31:0] $end
    $var wire 32 > reg_file[10] [31:0] $end
    $var wire 32 ? reg_file[11] [31:0] $end
    $var wire 32 @ reg_file[12] [31:0] $end
    $var wire 32 A reg_file[13] [31:0] $end
    $var wire 32 B reg_file[14] [31:0] $end
    $var wire 32 C reg_file[15] [31:0] $end
    $var wire 32 D reg_file[16] [31:0] $end
    $var wire 32 E reg_file[17] [31:0] $end
    $var wire 32 F reg_file[18] [31:0] $end
    $var wire 32 G reg_file[19] [31:0] $end
    $var wire 32 5 reg_file[1] [31:0] $end
    $var wire 32 H reg_file[20] [31:0] $end
    $var wire 32 I reg_file[21] [31:0] $end
    $var wire 32 J reg_file[22] [31:0] $end
    $var wire 32 K reg_file[23] [31:0] $end
    $var wire 32 L reg_file[24] [31:0] $end
    $var wire 32 M reg_file[25] [31:0] $end
    $var wire 32 N reg_file[26] [31:0] $end
    $var wire 32 O reg_file[27] [31:0] $end
    $var wire 32 P reg_file[28] [31:0] $end
    $var wire 32 Q reg_file[29] [31:0] $end
    $var wire 32 6 reg_file[2] [31:0] $end
    $var wire 32 R reg_file[30] [31:0] $end
    $var wire 32 S reg_file[31] [31:0] $end
    $var wire 32 7 reg_file[3] [31:0] $end
    $var wire 32 8 reg_file[4] [31:0] $end
    $var wire 32 9 reg_file[5] [31:0] $end
    $var wire 32 : reg_file[6] [31:0] $end
    $var wire 32 ; reg_file[7] [31:0] $end
    $var wire 32 < reg_file[8] [31:0] $end
    $var wire 32 = reg_file[9] [31:0] $end
    $var wire 32 U result [31:0] $end
    $var wire  1 ^ trigger $end
   $upscope $end
  $upscope $end
 $upscope $end
$enddefinitions $end


#0
b00000000000000000000000000000000 #
b00000000000000000000000000000000 $
0%
b0000 &
0'
0(
b000 )
b00000000000000000000000000000000 *
0+
0,
b000 -
b0000000 .
b0000000 /
b00000 0
b00000 1
b00000 2
b00000000000000000000000000000000 3
b00000000000000000000000000000000 4
b00000000000000000000000000000000 5
b00000000000000000000000000000000 6
b00000000000000000000000000000000 7
b00000000000000000000000000000000 8
b00000000000000000000000000000000 9
b00000000000000000000000000000000 :
b00000000000000000000000000000000 ;
b00000000000000000000000000000000 <
b00000000000000000000000000000000 =
b00000000000000000000000000000000 >
b00000000000000000000000000000000 ?
b00000000000000000000000000000000 @
b00000000000000000000000000000000 A
b00000000000000000000000000000000 B
b00000000000000000000000000000000 C
b00000000000000000000000000000000 D
b00000000000000000000000000000000 E
b00000000000000000000000000000000 F
b00000000000000000000000000000000 G
b00000000000000000000000000000000 H
b00000000000000000000000000000000 I
b00000000000000000000000000000000 J
b00000000000000000000000000000000 K
b00000000000000000000000000000000 L
b00000000000000000000000000000000 M
b00000000000000000000000000000000 N
b00000000000000000000000000000000 O
b00000000000000000000000000000000 P
b00000000000000000000000000000000 Q
b00000000000000000000000000000000 R
b00000000000000000000000000000000 S
b00000000000000000000000000000000 T
b00000000000000000000000000000000 U
b00 V
0W
b00000000000000000000000000000000 X
b00000000000000000000000000000000 Y
b00000000000000000000000000000000 Z
b00000000000000000000000000000000 [
0\
0]
0^
b00000000000000000000000000000000 _
b00000000000000000000000000100000 `
b00000000000000000000000000000101 a
b00000 b
b00000 c
b00000 d
b00000000000000000000000000000000 e
b00000000000000000000000000000000 f
#1
b00000000000000000000000000010000 $
1%
1'
b00000001000000000000010000010011 *
b0010011 /
b10000 1
b01000 2
b00000000000000000000000000010000 T
b00000000000000000000000000010000 U
b00000000000000000000000000010000 Z
b00000000000000000000000000010000 [
1\
#2
0\
1]
#3
b10111111110000000000000000000000 #
b00000000000000000000000000010000 <
1\
#4
0\
0]
#5
b10111111110000000000000000000100 #
b00000000000000000000000000000000 $
0%
0'
b010 )
b00000000000000101000000001100011 *
b1100011 /
b00101 0
b00000 1
b00000 2
b00000000000000000000000000000000 T
b00000000000000000000000000000000 U
b01 V
1W
b00000000000000000000000000000000 Z
b00000000000000000000000000000000 [
1\
#6
0\
#7
1\
#8
0\
#9
1\
#10
0\
#11
1\
#12
0\
#13
1\
#14
0\
#15
1\
#16
0\
#17
1\
#18
0\
#19
1\
#20
0\
#21
1\
#22
0\
#23
1\
#24
0\
#25
1\
#26
0\
#27
1\
#28
0\
#29
1\
#30
0\
#31
1\
#32
0\
#33
1\
#34
0\
#35
1\
#36
0\
#37
1\
#38
0\
#39
1\
#40
0\
#41
1\
#42
0\
#43
1\
#44
0\
#45
1\
#46
0\
#47
1\
#48
0\
#49
1\
#50
0\
#51
1\
#52
0\
#53
1\
#54
0\
#55
1\
#56
0\
#57
1\
#58
0\
#59
1\
#60
0\
#61
1\
#62
0\
#63
1\
#64
0\
#65
1\
#66
0\
#67
1\
#68
0\
#69
1\
#70
0\
#71
1\
#72
0\
#73
1\
#74
0\
#75
1\
#76
0\
#77
1\
#78
0\
#79
1\
#80
0\
#81
1\
#82
0\
#83
1\
#84
0\
#85
1\
#86
0\
#87
1\
#88
0\
#89
1\
#90
0\
#91
1\
#92
0\
#93
1\
#94
0\
#95
1\
#96
0\
#97
1\
#98
0\
#99
1\
#100
0\
#101
1\
#102
0\
#103
1\
#104
0\
#105
1\
#106
0\
1^
#107
b00000000000000000000000000000001 9
b00000000000000000000000000000001 T
b00000000000000000000000000000001 U
b00 V
0W
b00000000000000000000000000000001 X
b00000000000000000000000000000001 Z
1\
#108
0\
0^
#109
b10111111110000000000000000001000 #
1%
1'
b000 )
b00000000000000000000010110010011 *
b0010011 /
b00000 0
b01011 2
b00000000000000000000000000000000 9
b00000000000000000000000000000000 T
b00000000000000000000000000000000 U
1W
b00000000000000000000000000000000 X
b00000000000000000000000000000000 Z
1\
#110
0\
#111
b10111111110000000000000000001100 #
b00000000000000000000010100010011 *
b01010 2
1\
#112
0\
#113
b10111111110000000000000000010000 #
b00000000000000000000000000101000 $
b101 )
b00000010100000000000000011101111 *
1+
b0000001 .
b1101111 /
b01000 1
b00001 2
b10111111110000000000000000010100 T
b00000000000000000000000000101000 U
b01 V
0W
b00000000000000000000000000010000 Y
b00000000000000000000000000101000 Z
b00000000000000000000000000101000 [
1\
#114
0\
#115
b10111111110000000000000000111000 #
b00000000000000000000000000000000 $
b000 )
b00000000000000000000001100010011 *
0+
b0000000 .
b0010011 /
b00000 1
b00110 2
b10111111110000000000000000010100 5
b00000000000000000000000000000000 T
b00000000000000000000000000000000 U
b00 V
1W
b00000000000000000000000000000000 Y
b00000000000000000000000000000000 Z
b00000000000000000000000000000000 [
1\
#116
0\
#117
b10111111110000000000000000111100 #
b00000000000000000000000000000001 $
b00000000000100110000001100010011 *
b00110 0
b00001 1
b00000000000000000000000000000001 T
b00000000000000000000000000000001 U
0W
b10111111110000000000000000010100 Y
b00000000000000000000000000000001 Z
b00000000000000000000000000000001 [
1\
#118
0\
#119
b10111111110000000000000001000000 #
b11111111111111111111111111111100 $
0%
0'
b010 )
b11111110100000110001111011100011 *
b001 -
b1111111 .
b1100011 /
b01000 1
b11101 2
b00000000000000000000000000000001 :
b00000000000000000000000000010001 T
b00000000000000000000000000010001 U
b01 V
b00000000000000000000000000000001 X
b00000000000000000000000000010000 Y
b00000000000000000000000000010001 Z
b00000000000000000000000000010000 [
1\
#120
0\
#121
b10111111110000000000000000111100 #
b00000000000000000000000000000001 $
1%
1'
b000 )
b00000000000100110000001100010011 *
b000 -
b0000000 .
b0010011 /
b00001 1
b00110 2
b00000000000000000000000000000010 T
b00000000000000000000000000000010 U
b00 V
1W
b10111111110000000000000000010100 Y
b00000000000000000000000000000010 Z
b00000000000000000000000000000001 [
1\
#122
0\
#123
b10111111110000000000000001000000 #
b11111111111111111111111111111100 $
0%
0'
b010 )
b11111110100000110001111011100011 *
b001 -
b1111111 .
b1100011 /
b01000 1
b11101 2
b00000000000000000000000000000010 :
b00000000000000000000000000010010 T
b00000000000000000000000000010010 U
b01 V
0W
b00000000000000000000000000000010 X
b00000000000000000000000000010000 Y
b00000000000000000000000000010010 Z
b00000000000000000000000000010000 [
1\
#124
0\
#125
b10111111110000000000000000111100 #
b00000000000000000000000000000001 $
1%
1'
b000 )
b00000000000100110000001100010011 *
b000 -
b0000000 .
b0010011 /
b00001 1
b00110 2
b00000000000000000000000000000011 T
b00000000000000000000000000000011 U
b00 V
b10111111110000000000000000010100 Y
b00000000000000000000000000000011 Z
b00000000000000000000000000000001 [
1\
#126
0\
#127
b10111111110000000000000001000000 #
b11111111111111111111111111111100 $
0%
0'
b010 )
b11111110100000110001111011100011 *
b001 -
b1111111 .
b1100011 /
b01000 1
b11101 2
b00000000000000000000000000000011 :
b00000000000000000000000000010011 T
b00000000000000000000000000010011 U
b01 V
b00000000000000000000000000000011 X
b00000000000000000000000000010000 Y
b00000000000000000000000000010011 Z
b00000000000000000000000000010000 [
1\
#128
0\
#129
b10111111110000000000000000111100 #
b00000000000000000000000000000001 $
1%
1'
b000 )
b00000000000100110000001100010011 *
b000 -
b0000000 .
b0010011 /
b00001 1
b00110 2
b00000000000000000000000000000100 T
b00000000000000000000000000000100 U
b00 V
b10111111110000000000000000010100 Y
b00000000000000000000000000000100 Z
b00000000000000000000000000000001 [
1\
#130
0\
#131
b10111111110000000000000001000000 #
b11111111111111111111111111111100 $
0%
0'
b010 )
b11111110100000110001111011100011 *
b001 -
b1111111 .
b1100011 /
b01000 1
b11101 2
b00000000000000000000000000000100 :
b00000000000000000000000000010100 T
b00000000000000000000000000010100 U
b01 V
b00000000000000000000000000000100 X
b00000000000000000000000000010000 Y
b00000000000000000000000000010100 Z
b00000000000000000000000000010000 [
1\
#132
0\
#133
b10111111110000000000000000111100 #
b00000000000000000000000000000001 $
1%
1'
b000 )
b00000000000100110000001100010011 *
b000 -
b0000000 .
b0010011 /
b00001 1
b00110 2
b00000000000000000000000000000101 T
b00000000000000000000000000000101 U
b00 V
b10111111110000000000000000010100 Y
b00000000000000000000000000000101 Z
b00000000000000000000000000000001 [
1\
#134
0\
